MANIFEST.in
README.md
setup.py
bt_panel/__init__.py
bt_panel/daemon.py
bt_panel/log.py
bt_panel.egg-info/PKG-INFO
bt_panel.egg-info/SOURCES.txt
bt_panel.egg-info/dependency_links.txt
bt_panel.egg-info/entry_points.txt
bt_panel.egg-info/requires.txt
bt_panel.egg-info/top_level.txt